{
  "project_info": {
    "project_number": "52141628122",
    "project_id": "pdmchat-83952",
    "storage_bucket": "pdmchat-83952.appspot.com"
  },
  "client": [
    {
      "client_info": {
        "mobilesdk_app_id": "1:52141628122:android:ecfccd2cceec561bd863e3",
        "android_client_info": {
          "package_name": "com.example.pdmchat"
        }
      },
      "oauth_client": [],
      "api_key": [
        {
          "current_key": "AIzaSyD9lIaGi2bdWnAqu25IjiNgx6fOiKkTuhg"
        }
      ],
      "services": {
        "appinvite_service": {
          "other_platform_oauth_client": []
        }
      }
    }
  ],
  "configuration_version": "1"
}